aquests/__init__.py
aquests/lib.py
aquests/lifetime.py
aquests/queue.py
aquests/request_builder.py
aquests/response_builder.py
aquests/stubproxy.py
aquests/tl.py
aquests/athreads/__init__.py
aquests/athreads/fifo.py
aquests/athreads/select_trigger.py
aquests/athreads/socket_map.py
aquests/athreads/threadlib.py
aquests/athreads/trigger.py
aquests/athreads/trigger_file.py
aquests/client/__init__.py
aquests/client/adns.py
aquests/client/asynconnect.py
aquests/client/baseconnect.py
aquests/client/socketpool.py
aquests/client/synconnect.py
aquests/dbapi/__init__.py
aquests/dbapi/asynmongo.py
aquests/dbapi/asynpsycopg2.py
aquests/dbapi/asynredis.py
aquests/dbapi/dbconnect.py
aquests/dbapi/dbpool.py
aquests/dbapi/request.py
aquests/dbapi/syndbi.py
aquests/dbapi/synsqlite3.py
aquests/protocols/__init__.py
aquests/protocols/whois.py
aquests/protocols/dns/README-hans.txt
aquests/protocols/dns/__init__.py
aquests/protocols/dns/clients.py
aquests/protocols/dns/pydns/Base.py
aquests/protocols/dns/pydns/Class.py
aquests/protocols/dns/pydns/Lib.py
aquests/protocols/dns/pydns/Opcode.py
aquests/protocols/dns/pydns/README-guido.txt
aquests/protocols/dns/pydns/README.txt
aquests/protocols/dns/pydns/Status.py
aquests/protocols/dns/pydns/Type.py
aquests/protocols/dns/pydns/__init__.py
aquests/protocols/dns/pydns/lazy.py
aquests/protocols/dns/pydns/win32dns.py
aquests/protocols/grpc/__init__.py
aquests/protocols/grpc/buffers.py
aquests/protocols/grpc/discover.py
aquests/protocols/grpc/message.py
aquests/protocols/grpc/producers.py
aquests/protocols/grpc/request.py
aquests/protocols/http/__init__.py
aquests/protocols/http/base_request_handler.py
aquests/protocols/http/buffers.py
aquests/protocols/http/http_auth.py
aquests/protocols/http/http_date.py
aquests/protocols/http/http_util.py
aquests/protocols/http/localstorage.py
aquests/protocols/http/producer.py
aquests/protocols/http/request.py
aquests/protocols/http/request_handler.py
aquests/protocols/http/respcodes.py
aquests-0.30.2.dist-info/LICENSE
aquests-0.30.2.dist-info/METADATA
aquests-0.30.2.dist-info/WHEEL
aquests-0.30.2.dist-info/top_level.txt
aquests-0.30.2.dist-info/RECORD
