Metadata-Version: 2.1
Name: aquests
Version: 0.30.2
Summary: Asynchronous Multiplexing HTTP2/DBO Requests
Home-page: https://gitlab.com/skitai/aquests
Author: Hans Roh
Author-email: hansroh@gmail.com
License: MIT
Download-URL: https://pypi.python.org/pypi/aquests
Platform: posix
Platform: nt
Classifier: License :: OSI Approved :: MIT License
Classifier: Development Status :: 7 - Inactive
Classifier: Topic :: Internet :: WWW/HTTP
Classifier: Topic :: Database :: Front-Ends
Classifier: Environment :: Console
Classifier: Topic :: Software Development :: Libraries :: Python Modules
Classifier: Intended Audience :: Developers
Classifier: Intended Audience :: Science/Research
Classifier: Programming Language :: Python
Classifier: Programming Language :: Python :: 3
License-File: LICENSE
Requires-Dist: rs4
Requires-Dist: h2 (>=4.0.0)
